{
  "experiment_name": "COMPARING_MODELS",
  "split_methodology": "CVTT",
  "multiprocessing": "starmap",
  "n_jobs": 61,
  "checkpoint": "NO",
  "opt": "EVALUATION_METRICS",
  "metric": [
    "MAP",
    "MACE"
  ],
  "recommender": ["BPR", "ALS", "SVD", "POPULARITY_REC"],
  "dataset": ["food"],
  "fold": [1, 2, 3],
  "trial": [1],
  "tradeoff": ["TWOSTAGE"],
  "fairness": ["KL"],
  "relevance": ["SUM"],
  "weight": [
    "C@0.0", "C@0.1", "C@0.2",
    "C@0.3", "C@0.4", "C@0.5",
    "C@0.6", "C@0.7", "C@0.8",
    "C@0.9", "C@1.0"
  ],
  "distribution": [
    "CWS"
  ],
  "distribution_class": [
    "GENRE"
  ],
  "selector": ["SURROGATE"]
}
